LICENSE
README.md
pyproject.toml
undrdg/__init__.py
undrdg/parsers.py
undrdg/path.py
undrdg/tree.py
undrdg/utilities.py
undrdg/version.py
undrdg.egg-info/PKG-INFO
undrdg.egg-info/SOURCES.txt
undrdg.egg-info/dependency_links.txt
undrdg.egg-info/requires.txt
undrdg.egg-info/top_level.txt