Metadata-Version: 2.1
Name: undrdg
Version: 0.2.0
Summary: Generate datasets compatible with UNDR
Author-email: Alexandre Marcireau <alexandre.marcireau@gmail.com>
Classifier: Programming Language :: Python :: 3
Classifier: Operating System :: OS Independent
License-File: LICENSE
Requires-Dist: undr
